{"nodes": [{"id": "processor_recon_deep_headers_py", "label": "headers.py", "file_type": "code", "source_file": "processor\\recon\\deep\\headers.py", "source_location": "L1"}, {"id": "headers_banner", "label": "banner()", "file_type": "code", "source_file": "processor\\recon\\deep\\headers.py", "source_location": "L82"}, {"id": "headers_ok", "label": "ok()", "file_type": "code", "source_file": "processor\\recon\\deep\\headers.py", "source_location": "L85"}, {"id": "headers_warn", "label": "warn()", "file_type": "code", "source_file": "processor\\recon\\deep\\headers.py", "source_location": "L86"}, {"id": "headers_err", "label": "err()", "file_type": "code", "source_file": "processor\\recon\\deep\\headers.py", "source_location": "L87"}, {"id": "headers_info", "label": "info()", "file_type": "code", "source_file": "processor\\recon\\deep\\headers.py", "source_location": "L88"}, {"id": "headers_fetch_headers", "label": "fetch_headers()", "file_type": "code", "source_file": "processor\\recon\\deep\\headers.py", "source_location": "L91"}, {"id": "headers_audit_csp", "label": "audit_csp()", "file_type": "code", "source_file": "processor\\recon\\deep\\headers.py", "source_location": "L101"}, {"id": "headers_analyze_headers", "label": "analyze_headers()", "file_type": "code", "source_file": "processor\\recon\\deep\\headers.py", "source_location": "L110"}, {"id": "headers_process", "label": "process()", "file_type": "code", "source_file": "processor\\recon\\deep\\headers.py", "source_location": "L152"}, {"id": "headers_rationale_92", "label": "Fetch HTTP response headers from a URL.", "file_type": "rationale", "source_file": "processor\\recon\\deep\\headers.py", "source_location": "L92"}, {"id": "headers_rationale_102", "label": "Audit a CSP value for weak directives.", "file_type": "rationale", "source_file": "processor\\recon\\deep\\headers.py", "source_location": "L102"}, {"id": "headers_rationale_111", "label": "Analyze response headers against security checklist.", "file_type": "rationale", "source_file": "processor\\recon\\deep\\headers.py", "source_location": "L111"}], "edges": [{"source": "processor_recon_deep_headers_py", "target": "requests", "relation": "imports", "confidence": "EXTRACTED", "source_file": "processor\\recon\\deep\\headers.py", "source_location": "L7", "weight": 1.0}, {"source": "processor_recon_deep_headers_py", "target": "json", "relation": "imports", "confidence": "EXTRACTED", "source_file": "processor\\recon\\deep\\headers.py", "source_location": "L8", "weight": 1.0}, {"source": "processor_recon_deep_headers_py", "target": "sys", "relation": "imports", "confidence": "EXTRACTED", "source_file": "processor\\recon\\deep\\headers.py", "source_location": "L9", "weight": 1.0}, {"source": "processor_recon_deep_headers_py", "target": "datetime", "relation": "imports_from", "confidence": "EXTRACTED", "source_file": "processor\\recon\\deep\\headers.py", "source_location": "L10", "weight": 1.0}, {"source": "processor_recon_deep_headers_py", "target": "colorama", "relation": "imports_from", "confidence": "EXTRACTED", "source_file": "processor\\recon\\deep\\headers.py", "source_location": "L11", "weight": 1.0}, {"source": "processor_recon_deep_headers_py", "target": "urllib3", "relation": "imports", "confidence": "EXTRACTED", "source_file": "processor\\recon\\deep\\headers.py", "source_location": "L12", "weight": 1.0}, {"source": "processor_recon_deep_headers_py", "target": "headers_banner", "relation": "contains", "confidence": "EXTRACTED", "source_file": "processor\\recon\\deep\\headers.py", "source_location": "L82", "weight": 1.0}, {"source": "processor_recon_deep_headers_py", "target": "headers_ok", "relation": "contains", "confidence": "EXTRACTED", "source_file": "processor\\recon\\deep\\headers.py", "source_location": "L85", "weight": 1.0}, {"source": "processor_recon_deep_headers_py", "target": "headers_warn", "relation": "contains", "confidence": "EXTRACTED", "source_file": "processor\\recon\\deep\\headers.py", "source_location": "L86", "weight": 1.0}, {"source": "processor_recon_deep_headers_py", "target": "headers_err", "relation": "contains", "confidence": "EXTRACTED", "source_file": "processor\\recon\\deep\\headers.py", "source_location": "L87", "weight": 1.0}, {"source": "processor_recon_deep_headers_py", "target": "headers_info", "relation": "contains", "confidence": "EXTRACTED", "source_file": "processor\\recon\\deep\\headers.py", "source_location": "L88", "weight": 1.0}, {"source": "processor_recon_deep_headers_py", "target": "headers_fetch_headers", "relation": "contains", "confidence": "EXTRACTED", "source_file": "processor\\recon\\deep\\headers.py", "source_location": "L91", "weight": 1.0}, {"source": "processor_recon_deep_headers_py", "target": "headers_audit_csp", "relation": "contains", "confidence": "EXTRACTED", "source_file": "processor\\recon\\deep\\headers.py", "source_location": "L101", "weight": 1.0}, {"source": "processor_recon_deep_headers_py", "target": "headers_analyze_headers", "relation": "contains", "confidence": "EXTRACTED", "source_file": "processor\\recon\\deep\\headers.py", "source_location": "L110", "weight": 1.0}, {"source": "processor_recon_deep_headers_py", "target": "headers_process", "relation": "contains", "confidence": "EXTRACTED", "source_file": "processor\\recon\\deep\\headers.py", "source_location": "L152", "weight": 1.0}, {"source": "headers_analyze_headers", "target": "headers_audit_csp", "relation": "calls", "confidence": "EXTRACTED", "source_file": "processor\\recon\\deep\\headers.py", "source_location": "L132", "weight": 1.0}, {"source": "headers_analyze_headers", "target": "headers_warn", "relation": "calls", "confidence": "EXTRACTED", "source_file": "processor\\recon\\deep\\headers.py", "source_location": "L134", "weight": 1.0}, {"source": "headers_analyze_headers", "target": "headers_ok", "relation": "calls", "confidence": "EXTRACTED", "source_file": "processor\\recon\\deep\\headers.py", "source_location": "L136", "weight": 1.0}, {"source": "headers_analyze_headers", "target": "headers_err", "relation": "calls", "confidence": "EXTRACTED", "source_file": "processor\\recon\\deep\\headers.py", "source_location": "L142", "weight": 1.0}, {"source": "headers_process", "target": "headers_banner", "relation": "calls", "confidence": "EXTRACTED", "source_file": "processor\\recon\\deep\\headers.py", "source_location": "L153", "weight": 1.0}, {"source": "headers_process", "target": "headers_info", "relation": "calls", "confidence": "EXTRACTED", "source_file": "processor\\recon\\deep\\headers.py", "source_location": "L154", "weight": 1.0}, {"source": "headers_process", "target": "headers_fetch_headers", "relation": "calls", "confidence": "EXTRACTED", "source_file": "processor\\recon\\deep\\headers.py", "source_location": "L166", "weight": 1.0}, {"source": "headers_process", "target": "headers_warn", "relation": "calls", "confidence": "EXTRACTED", "source_file": "processor\\recon\\deep\\headers.py", "source_location": "L169", "weight": 1.0}, {"source": "headers_process", "target": "headers_ok", "relation": "calls", "confidence": "EXTRACTED", "source_file": "processor\\recon\\deep\\headers.py", "source_location": "L172", "weight": 1.0}, {"source": "headers_process", "target": "headers_analyze_headers", "relation": "calls", "confidence": "EXTRACTED", "source_file": "processor\\recon\\deep\\headers.py", "source_location": "L174", "weight": 1.0}, {"source": "headers_process", "target": "headers_err", "relation": "calls", "confidence": "EXTRACTED", "source_file": "processor\\recon\\deep\\headers.py", "source_location": "L202", "weight": 1.0}, {"source": "headers_rationale_92", "target": "headers_fetch_headers", "relation": "rationale_for", "confidence": "EXTRACTED", "source_file": "processor\\recon\\deep\\headers.py", "source_location": "L92", "weight": 1.0}, {"source": "headers_rationale_102", "target": "headers_audit_csp", "relation": "rationale_for", "confidence": "EXTRACTED", "source_file": "processor\\recon\\deep\\headers.py", "source_location": "L102", "weight": 1.0}, {"source": "headers_rationale_111", "target": "headers_analyze_headers", "relation": "rationale_for", "confidence": "EXTRACTED", "source_file": "processor\\recon\\deep\\headers.py", "source_location": "L111", "weight": 1.0}], "raw_calls": [{"caller_nid": "headers_banner", "callee": "print", "source_file": "processor\\recon\\deep\\headers.py", "source_location": "L83"}, {"caller_nid": "headers_ok", "callee": "print", "source_file": "processor\\recon\\deep\\headers.py", "source_location": "L85"}, {"caller_nid": "headers_warn", "callee": "print", "source_file": "processor\\recon\\deep\\headers.py", "source_location": "L86"}, {"caller_nid": "headers_err", "callee": "print", "source_file": "processor\\recon\\deep\\headers.py", "source_location": "L87"}, {"caller_nid": "headers_info", "callee": "print", "source_file": "processor\\recon\\deep\\headers.py", "source_location": "L88"}, {"caller_nid": "headers_fetch_headers", "callee": "get", "source_file": "processor\\recon\\deep\\headers.py", "source_location": "L94"}, {"caller_nid": "headers_fetch_headers", "callee": "str", "source_file": "processor\\recon\\deep\\headers.py", "source_location": "L96"}, {"caller_nid": "headers_fetch_headers", "callee": "str", "source_file": "processor\\recon\\deep\\headers.py", "source_location": "L98"}, {"caller_nid": "headers_audit_csp", "callee": "append", "source_file": "processor\\recon\\deep\\headers.py", "source_location": "L106"}, {"caller_nid": "headers_analyze_headers", "callee": "len", "source_file": "processor\\recon\\deep\\headers.py", "source_location": "L115"}, {"caller_nid": "headers_analyze_headers", "callee": "items", "source_file": "processor\\recon\\deep\\headers.py", "source_location": "L117"}, {"caller_nid": "headers_analyze_headers", "callee": "get", "source_file": "processor\\recon\\deep\\headers.py", "source_location": "L118"}, {"caller_nid": "headers_analyze_headers", "callee": "len", "source_file": "processor\\recon\\deep\\headers.py", "source_location": "L138"}, {"caller_nid": "headers_analyze_headers", "callee": "append", "source_file": "processor\\recon\\deep\\headers.py", "source_location": "L141"}, {"caller_nid": "headers_analyze_headers", "callee": "round", "source_file": "processor\\recon\\deep\\headers.py", "source_location": "L148"}, {"caller_nid": "headers_process", "callee": "isoformat", "source_file": "processor\\recon\\deep\\headers.py", "source_location": "L158"}, {"caller_nid": "headers_process", "callee": "now", "source_file": "processor\\recon\\deep\\headers.py", "source_location": "L158"}, {"caller_nid": "headers_process", "callee": "upper", "source_file": "processor\\recon\\deep\\headers.py", "source_location": "L173"}, {"caller_nid": "headers_process", "callee": "dict", "source_file": "processor\\recon\\deep\\headers.py", "source_location": "L182"}, {"caller_nid": "headers_process", "callee": "get", "source_file": "processor\\recon\\deep\\headers.py", "source_location": "L190"}, {"caller_nid": "headers_process", "callee": "get", "source_file": "processor\\recon\\deep\\headers.py", "source_location": "L190"}, {"caller_nid": "headers_process", "callee": "get", "source_file": "processor\\recon\\deep\\headers.py", "source_location": "L192"}, {"caller_nid": "headers_process", "callee": "get", "source_file": "processor\\recon\\deep\\headers.py", "source_location": "L193"}, {"caller_nid": "headers_process", "callee": "len", "source_file": "processor\\recon\\deep\\headers.py", "source_location": "L194"}, {"caller_nid": "headers_process", "callee": "print", "source_file": "processor\\recon\\deep\\headers.py", "source_location": "L200"}]}