{"nodes": [{"id": "processor_recon_deep_emailsecurity_py", "label": "emailsecurity.py", "file_type": "code", "source_file": "processor\\recon\\deep\\emailsecurity.py", "source_location": "L1"}, {"id": "emailsecurity_check_spf", "label": "check_spf()", "file_type": "code", "source_file": "processor\\recon\\deep\\emailsecurity.py", "source_location": "L10"}, {"id": "emailsecurity_check_dmarc", "label": "check_dmarc()", "file_type": "code", "source_file": "processor\\recon\\deep\\emailsecurity.py", "source_location": "L29"}, {"id": "emailsecurity_check_dkim", "label": "check_dkim()", "file_type": "code", "source_file": "processor\\recon\\deep\\emailsecurity.py", "source_location": "L73"}, {"id": "emailsecurity_process", "label": "process()", "file_type": "code", "source_file": "processor\\recon\\deep\\emailsecurity.py", "source_location": "L91"}, {"id": "emailsecurity_rationale_92", "label": "Entry point for pipeline.py", "file_type": "rationale", "source_file": "processor\\recon\\deep\\emailsecurity.py", "source_location": "L92"}], "edges": [{"source": "processor_recon_deep_emailsecurity_py", "target": "sys", "relation": "imports", "confidence": "EXTRACTED", "source_file": "processor\\recon\\deep\\emailsecurity.py", "source_location": "L2", "weight": 1.0}, {"source": "processor_recon_deep_emailsecurity_py", "target": "dns_resolver", "relation": "imports", "confidence": "EXTRACTED", "source_file": "processor\\recon\\deep\\emailsecurity.py", "source_location": "L3", "weight": 1.0}, {"source": "processor_recon_deep_emailsecurity_py", "target": "colorama", "relation": "imports_from", "confidence": "EXTRACTED", "source_file": "processor\\recon\\deep\\emailsecurity.py", "source_location": "L4", "weight": 1.0}, {"source": "processor_recon_deep_emailsecurity_py", "target": "emailsecurity_check_spf", "relation": "contains", "confidence": "EXTRACTED", "source_file": "processor\\recon\\deep\\emailsecurity.py", "source_location": "L10", "weight": 1.0}, {"source": "processor_recon_deep_emailsecurity_py", "target": "emailsecurity_check_dmarc", "relation": "contains", "confidence": "EXTRACTED", "source_file": "processor\\recon\\deep\\emailsecurity.py", "source_location": "L29", "weight": 1.0}, {"source": "processor_recon_deep_emailsecurity_py", "target": "emailsecurity_check_dkim", "relation": "contains", "confidence": "EXTRACTED", "source_file": "processor\\recon\\deep\\emailsecurity.py", "source_location": "L73", "weight": 1.0}, {"source": "processor_recon_deep_emailsecurity_py", "target": "emailsecurity_process", "relation": "contains", "confidence": "EXTRACTED", "source_file": "processor\\recon\\deep\\emailsecurity.py", "source_location": "L91", "weight": 1.0}, {"source": "emailsecurity_process", "target": "emailsecurity_check_spf", "relation": "calls", "confidence": "EXTRACTED", "source_file": "processor\\recon\\deep\\emailsecurity.py", "source_location": "L95", "weight": 1.0}, {"source": "emailsecurity_process", "target": "emailsecurity_check_dmarc", "relation": "calls", "confidence": "EXTRACTED", "source_file": "processor\\recon\\deep\\emailsecurity.py", "source_location": "L96", "weight": 1.0}, {"source": "emailsecurity_process", "target": "emailsecurity_check_dkim", "relation": "calls", "confidence": "EXTRACTED", "source_file": "processor\\recon\\deep\\emailsecurity.py", "source_location": "L97", "weight": 1.0}, {"source": "emailsecurity_rationale_92", "target": "emailsecurity_process", "relation": "rationale_for", "confidence": "EXTRACTED", "source_file": "processor\\recon\\deep\\emailsecurity.py", "source_location": "L92", "weight": 1.0}], "raw_calls": [{"caller_nid": "emailsecurity_check_spf", "callee": "print", "source_file": "processor\\recon\\deep\\emailsecurity.py", "source_location": "L11"}, {"caller_nid": "emailsecurity_check_spf", "callee": "resolve", "source_file": "processor\\recon\\deep\\emailsecurity.py", "source_location": "L13"}, {"caller_nid": "emailsecurity_check_spf", "callee": "strip", "source_file": "processor\\recon\\deep\\emailsecurity.py", "source_location": "L15"}, {"caller_nid": "emailsecurity_check_spf", "callee": "str", "source_file": "processor\\recon\\deep\\emailsecurity.py", "source_location": "L15"}, {"caller_nid": "emailsecurity_check_spf", "callee": "startswith", "source_file": "processor\\recon\\deep\\emailsecurity.py", "source_location": "L16"}, {"caller_nid": "emailsecurity_check_spf", "callee": "print", "source_file": "processor\\recon\\deep\\emailsecurity.py", "source_location": "L18"}, {"caller_nid": "emailsecurity_check_spf", "callee": "print", "source_file": "processor\\recon\\deep\\emailsecurity.py", "source_location": "L20"}, {"caller_nid": "emailsecurity_check_spf", "callee": "print", "source_file": "processor\\recon\\deep\\emailsecurity.py", "source_location": "L22"}, {"caller_nid": "emailsecurity_check_spf", "callee": "print", "source_file": "processor\\recon\\deep\\emailsecurity.py", "source_location": "L25"}, {"caller_nid": "emailsecurity_check_dmarc", "callee": "print", "source_file": "processor\\recon\\deep\\emailsecurity.py", "source_location": "L30"}, {"caller_nid": "emailsecurity_check_dmarc", "callee": "resolve", "source_file": "processor\\recon\\deep\\emailsecurity.py", "source_location": "L33"}, {"caller_nid": "emailsecurity_check_dmarc", "callee": "strip", "source_file": "processor\\recon\\deep\\emailsecurity.py", "source_location": "L35"}, {"caller_nid": "emailsecurity_check_dmarc", "callee": "str", "source_file": "processor\\recon\\deep\\emailsecurity.py", "source_location": "L35"}, {"caller_nid": "emailsecurity_check_dmarc", "callee": "startswith", "source_file": "processor\\recon\\deep\\emailsecurity.py", "source_location": "L36"}, {"caller_nid": "emailsecurity_check_dmarc", "callee": "print", "source_file": "processor\\recon\\deep\\emailsecurity.py", "source_location": "L46"}, {"caller_nid": "emailsecurity_check_dmarc", "callee": "print", "source_file": "processor\\recon\\deep\\emailsecurity.py", "source_location": "L49"}, {"caller_nid": "emailsecurity_check_dmarc", "callee": "print", "source_file": "processor\\recon\\deep\\emailsecurity.py", "source_location": "L52"}, {"caller_nid": "emailsecurity_check_dmarc", "callee": "print", "source_file": "processor\\recon\\deep\\emailsecurity.py", "source_location": "L56"}, {"caller_nid": "emailsecurity_check_dmarc", "callee": "print", "source_file": "processor\\recon\\deep\\emailsecurity.py", "source_location": "L59"}, {"caller_nid": "emailsecurity_check_dmarc", "callee": "print", "source_file": "processor\\recon\\deep\\emailsecurity.py", "source_location": "L62"}, {"caller_nid": "emailsecurity_check_dmarc", "callee": "print", "source_file": "processor\\recon\\deep\\emailsecurity.py", "source_location": "L66"}, {"caller_nid": "emailsecurity_check_dmarc", "callee": "print", "source_file": "processor\\recon\\deep\\emailsecurity.py", "source_location": "L69"}, {"caller_nid": "emailsecurity_check_dkim", "callee": "print", "source_file": "processor\\recon\\deep\\emailsecurity.py", "source_location": "L74"}, {"caller_nid": "emailsecurity_check_dkim", "callee": "resolve", "source_file": "processor\\recon\\deep\\emailsecurity.py", "source_location": "L79"}, {"caller_nid": "emailsecurity_check_dkim", "callee": "strip", "source_file": "processor\\recon\\deep\\emailsecurity.py", "source_location": "L81"}, {"caller_nid": "emailsecurity_check_dkim", "callee": "str", "source_file": "processor\\recon\\deep\\emailsecurity.py", "source_location": "L81"}, {"caller_nid": "emailsecurity_check_dkim", "callee": "startswith", "source_file": "processor\\recon\\deep\\emailsecurity.py", "source_location": "L82"}, {"caller_nid": "emailsecurity_check_dkim", "callee": "print", "source_file": "processor\\recon\\deep\\emailsecurity.py", "source_location": "L83"}, {"caller_nid": "emailsecurity_check_dkim", "callee": "print", "source_file": "processor\\recon\\deep\\emailsecurity.py", "source_location": "L87"}]}